altair_latimes/__init__.py
altair_latimes-0.0.2.dist-info/LICENSE
altair_latimes-0.0.2.dist-info/METADATA
altair_latimes-0.0.2.dist-info/WHEEL
altair_latimes-0.0.2.dist-info/top_level.txt
altair_latimes-0.0.2.dist-info/RECORD
