Metadata-Version: 2.1
Name: altair-latimes
Version: 0.0.2
Summary: A Los Angeles Times theme for Python's Altair statistical visualization library
Home-page: http://www.github.com/datadesk/altair-latimes/
Author: The Los Angeles Times Data Desk
Author-email: datadesk@latimes.com
License: MIT
Platform: UNKNOWN
Classifier: Development Status :: 5 - Production/Stable
Classifier: Programming Language :: Python
Classifier: Programming Language :: Python :: 2
Classifier: Programming Language :: Python :: 2.7
Classifier: Programming Language :: Python :: 3
Classifier: Programming Language :: Python :: 3.6
Classifier: Programming Language :: Python :: 3.7
Classifier: License :: OSI Approved :: MIT License
